{
    "STAGE": "initial",
    "STREETS":
        {"S_2_2": {"position": {"x": 2, "y": 2}, "size": {"width": 1, "height": 1},
                   "adjacent": {"down": "S_2_3", "right": "S_3_2"}, "function": "None"},
         "S_3_2": {"position": {"x": 3, "y": 2}, "size": {"width": 1, "height": 1},
                   "adjacent": {"left": "S_2_2", "right": "S_4_2"}, "function": "P_3_1"},
         "S_4_2": {"position": {"x": 4, "y": 2}, "size": {"width": 1, "height": 1},
                   "adjacent": {"down": "S_4_3", "left": "S_3_2", "right": "S_5_2"}, "function": "P_4_1"},
         "S_5_2": {"position": {"x": 5, "y": 2}, "size": {"width": 1, "height": 1},
                   "adjacent": {"left": "S_4_2", "right": "S_6_2"}, "function": "P_5_1"},
         "S_6_2": {"position": {"x": 6, "y": 2}, "size": {"width": 1, "height": 1},
                   "adjacent": {"down": "S_6_3", "left": "S_5_2"}, "function": "None"},
         "S_2_3": {"position": {"x": 2, "y": 3}, "size": {"width": 1, "height": 1},
                   "adjacent": {"up": "S_2_2", "down": "S_2_4"}, "function": "P_1_3"},
         "S_4_3": {"position": {"x": 4, "y": 3}, "size": {"width": 1, "height": 1},
                   "adjacent": {"up": "S_4_2", "down": "S_4_4"}, "function": "None"},
         "S_6_3": {"position": {"x": 6, "y": 3}, "size": {"width": 1, "height": 1},
                   "adjacent": {"up": "S_6_2", "down": "S_6_4"}, "function": "P_7_3"},
         "S_2_4": {"position": {"x": 2, "y": 4}, "size": {"width": 1, "height": 1},
                   "adjacent": {"up": "S_2_3", "down": "S_2_5"}, "function": "P_1_4"},
         "S_4_4": {"position": {"x": 4, "y": 4}, "size": {"width": 1, "height": 1},
                   "adjacent": {"up": "S_4_3", "down": "S_4_5"}, "function": "None"},
         "S_6_4": {"position": {"x": 6, "y": 4}, "size": {"width": 1, "height": 1},
                   "adjacent": {"up": "S_6_3", "down": "S_6_5"}, "function": "P_7_4"},
         "S_2_5": {"position": {"x": 2, "y": 5}, "size": {"width": 1, "height": 1},
                   "adjacent": {"up": "S_2_4", "right": "S_3_5"}, "function": "None"},
         "S_3_5": {"position": {"x": 3, "y": 5}, "size": {"width": 1, "height": 1},
                   "adjacent": {"left": "S_2_5", "right": "S_4_5"}, "function": "P_3_6"},
         "S_4_5": {"position": {"x": 4, "y": 5}, "size": {"width": 1, "height": 1},
                   "adjacent": {"up": "S_4_4", "left": "S_3_5", "right": "S_5_5"}, "function": "P_4_6"},
         "S_5_5": {"position": {"x": 5, "y": 5}, "size": {"width": 1, "height": 1},
                   "adjacent": {"left": "S_4_5", "right": "S_6_5"}, "function": "P_5_6"},
         "S_6_5": {"position": {"x": 6, "y": 5}, "size": {"width": 1, "height": 1},
                   "adjacent": {"up": "S_6_4", "left": "S_5_5"}, "function": "None"}},
    "PROPERTIES":
        {"P_3_1": {"position": {"x": 3, "y": 1}, "size": {"width": 1, "height": 1}, "street": "S_3_2", "ini_price": 10,
                   "rental": [[2, 3, 4], [3, 5, 7], [4, 7, 10]], "build_cost": [6, 8]},
         "P_4_1": {"position": {"x": 4, "y": 1}, "size": {"width": 1, "height": 1}, "street": "S_4_2", "ini_price": 10,
                   "rental": [[2, 3, 4], [3, 5, 7], [4, 7, 10]], "build_cost": [6, 8]},
         "P_5_1": {"position": {"x": 5, "y": 1}, "size": {"width": 1, "height": 1}, "street": "S_5_2", "ini_price": 10,
                   "rental": [[2, 3, 4], [3, 5, 7], [4, 7, 10]], "build_cost": [6, 8]},
         "P_1_3": {"position": {"x": 1, "y": 3}, "size": {"width": 1, "height": 1}, "street": "S_2_3", "ini_price": 10,
                   "rental": [[2, 3, 4], [3, 5, 7], [4, 7, 10]], "build_cost": [6, 8]},
         "P_7_3": {"position": {"x": 7, "y": 3}, "size": {"width": 1, "height": 1}, "street": "S_6_3", "ini_price": 10,
                   "rental": [[2, 3, 4], [3, 5, 7], [4, 7, 10]], "build_cost": [6, 8]},
         "P_1_4": {"position": {"x": 1, "y": 4}, "size": {"width": 1, "height": 1}, "street": "S_2_4", "ini_price": 10,
                   "rental": [[2, 3, 4], [3, 5, 7], [4, 7, 10]], "build_cost": [6, 8]},
         "P_7_4": {"position": {"x": 7, "y": 4}, "size": {"width": 1, "height": 1}, "street": "S_6_4", "ini_price": 10,
                   "rental": [[2, 3, 4], [3, 5, 7], [4, 7, 10]], "build_cost": [6, 8]},
         "P_3_6": {"position": {"x": 3, "y": 6}, "size": {"width": 1, "height": 1}, "street": "S_3_5", "ini_price": 10,
                   "rental": [[2, 3, 4], [3, 5, 7], [4, 7, 10]], "build_cost": [6, 8]},
         "P_4_6": {"position": {"x": 4, "y": 6}, "size": {"width": 1, "height": 1}, "street": "S_4_5", "ini_price": 10,
                   "rental": [[2, 3, 4], [3, 5, 7], [4, 7, 10]], "build_cost": [6, 8]},
         "P_5_6": {"position": {"x": 5, "y": 6}, "size": {"width": 1, "height": 1}, "street": "S_5_5", "ini_price": 10,
                   "rental": [[2, 3, 4], [3, 5, 7], [4, 7, 10]], "build_cost": [6, 8]}},
    "CARDS": {},
    "PLAYERS": {
        "1": {
            "position": "S_2_2",
            "cash": 100,
            "direction": "right",
        },
        "2": {
            "position": "S_6_4",
            "cash": 100,
            "direction": "down",
        },
        "3": {
            "position": "S_3_5",
            "cash": 100,
            "direction": "left",
        },
        "4": {
            "position": "S_6_3",
            "cash": 100,
            "direction": "up",
        }
    },
    "CRISIS_RATIO": 1
}